{"teamList": [
    {
        "playerList": [{"name": "Luka Doncic"}],
        "name": "a"
    },
    {
        "playerList": [{"name": "Lebron James"}],
        "name": "b"
    },
    {
        "playerList": [{"name": "Kawhi Leonard"}],
        "name": "c"
    },
    {
        "playerList": [{"name": "James Harden"}],
        "name": "d"
    },
    {
        "playerList": [{"name": "James Harden"}],
        "name": "e"
    },
    {
        "playerList": [{"name": "Mike Conley"}],
        "name": "f"
    }
]}